currency_rates_cbr/__init__.py
currency_rates_cbr/cli.py
currency_rates_cbr/controller.py
currency_rates_cbr/database.py
currency_rates_cbr/model.py
currency_rates_cbr/view.py
currency_rates_cbr-1.0.0.dist-info/licenses/LICENSE
currency_rates_cbr-1.0.0.dist-info/METADATA
currency_rates_cbr-1.0.0.dist-info/WHEEL
currency_rates_cbr-1.0.0.dist-info/entry_points.txt
currency_rates_cbr-1.0.0.dist-info/top_level.txt
currency_rates_cbr-1.0.0.dist-info/RECORD
